dg_mol_track_client/__init__.py
dg_mol_track_client/_version.py
dg_mol_track_client/additions.py
dg_mol_track_client/admin.py
dg_mol_track_client/assayresults.py
dg_mol_track_client/assayruns.py
dg_mol_track_client/assays.py
dg_mol_track_client/automapcolumns.py
dg_mol_track_client/basesdk.py
dg_mol_track_client/batches.py
dg_mol_track_client/compounds.py
dg_mol_track_client/httpclient.py
dg_mol_track_client/py.typed
dg_mol_track_client/schema.py
dg_mol_track_client/schemabatches.py
dg_mol_track_client/sdk.py
dg_mol_track_client/sdkconfiguration.py
dg_mol_track_client/search.py
dg_mol_track_client/search_assayruns.py
dg_mol_track_client/search_assays.py
dg_mol_track_client/search_batches.py
dg_mol_track_client/settings.py
dg_mol_track_client/users.py
dg_mol_track_client/validators.py
dg_mol_track_client/_hooks/__init__.py
dg_mol_track_client/_hooks/registration.py
dg_mol_track_client/_hooks/sdkhooks.py
dg_mol_track_client/_hooks/types.py
dg_mol_track_client/errors/__init__.py
dg_mol_track_client/errors/httpvalidationerror.py
dg_mol_track_client/errors/moltrackclientdefaulterror.py
dg_mol_track_client/errors/moltrackclienterror.py
dg_mol_track_client/errors/no_response_error.py
dg_mol_track_client/errors/responsevalidationerror.py
dg_mol_track_client/models/__init__.py
dg_mol_track_client/models/addition.py
dg_mol_track_client/models/additionbase.py
dg_mol_track_client/models/additionsrole.py
dg_mol_track_client/models/additionupdate.py
dg_mol_track_client/models/aggregation.py
dg_mol_track_client/models/aggregationnumericop.py
dg_mol_track_client/models/aggregationstringop.py
dg_mol_track_client/models/assay.py
dg_mol_track_client/models/assaycreatebase.py
dg_mol_track_client/models/assayproperty.py
dg_mol_track_client/models/assayresponse.py
dg_mol_track_client/models/assayresultproperty.py
dg_mol_track_client/models/assayresultresponse.py
dg_mol_track_client/models/assayrundetail.py
dg_mol_track_client/models/assayrunresponse.py
dg_mol_track_client-0.0.1.dist-info/METADATA
dg_mol_track_client-0.0.1.dist-info/WHEEL
dg_mol_track_client-0.0.1.dist-info/top_level.txt
dg_mol_track_client-0.0.1.dist-info/RECORD
